generate_pyproject/__init__.py
generate_pyproject/generate_pyproject.py
ste_beta_gp-0.0.7.dist-info/METADATA
ste_beta_gp-0.0.7.dist-info/WHEEL
ste_beta_gp-0.0.7.dist-info/top_level.txt
ste_beta_gp-0.0.7.dist-info/RECORD
