Metadata-Version: 2.1
Name: ste-beta-gp
Version: 0.0.7
Summary: Generate needed pyproject files to use with setuptools
